Metadata-Version: 2.1
Name: word2num-de
Version: 1.1
Summary: Transforms written numbers in German to numbers.
Home-page: https://github.com/kaorusss/word2num-de
Author: Kaoru Schwarzenegger
License: MIT
Download-URL: https://github.com/kaorusss/word2num-de/archive/v1.1.tar.gz
Keywords: numbers,convert,words,german
Platform: UNKNOWN
Classifier: Intended Audience :: Developers
Classifier: Programming Language :: Python
